{
  "slug": "2026-07-01-feature-highlight-dreamnest-ai",
  "title": "Feature Highlight: DreamNest AI \u2013 Your Personal Sleep Companion",
  "excerpt": "Discover how DreamNest AI can transform your sleep experience with personalized recommendations.",
  "category": "App Update",
  "body": "As summer nights roll in, we know how important a restful sleep is amidst the warmth and longer days. Today, we\u2019re excited to highlight our latest feature in the DreamNest app that harnesses the power of AI to create a personalized sleep environment tailored just for you. With DreamNest AI, our goal is to not just help you sleep sounder, but also to enhance your overall wellbeing by making your nightly routine smarter and more efficient.\n\nDreamNest AI utilizes advanced algorithms to analyze your sleep patterns based on data input from previous nights. The app will suggest an optimal wind-down routine, ideal room temperatures, and even recommend soothing sounds to help you fall asleep quicker. With its machine learning capabilities, DreamNest continually improves its recommendations, adapting to your ever-changing needs and preferences, ensuring that each night is spent in tranquility.\n\nIn addition to these features, DreamNest AI includes a sleep journal that allows you to log factors affecting your sleep, from diet and exercise to bedtime habits. With this holistic overview, you gain insights into how your lifestyle choices impact your sleep quality, empowering you to make informed changes. We believe that understanding your habits is key to better sleep, and our AI-driven features make that transformation easier than ever.\n\nWe can't wait for users to experience the power of personalized sleep with DreamNest AI. Update to the latest version today, and unlock these features to start your journey towards a more restful and rejuvenating night\u2019s sleep. Sweet dreams await!",
  "date": "2026-07-01T16:27:57+06:00"
}